{
  "$schema": "http://schema.management.azure.com/schemas/2015-01-01/deploymentParameters.json#",
  "contentVersion": "1.0.0.0",
  "parameters": {
    "input": {
      "value": {
        "Id": "/providers/Microsoft.Management/managementGroups/ES-identity",
        "Type": "/providers/Microsoft.Management/managementGroups",
        "Name": "ES-identity",
        "TenantId": "bb4c9e42-b982-4573-8741-cb71d8b92af4",
        "DisplayName": "Identity",
        "UpdatedTime": "0001-01-01T00:00:00Z",
        "UpdatedBy": null,
        "ParentId": "/providers/Microsoft.Management/managementGroups/ES-platform",
        "ParentName": "ES-platform",
        "ParentDisplayName": "ES-platform",
        "Children": null,
        "properties": {
          "policyDefinitions": [],
          "policySetDefinitions": [],
          "policyAssignments": [],
          "roleDefinitions": [],
          "roleAssignments": [
            {
              "Id": "/providers/Microsoft.Management/managementGroups/ES-identity/providers/Microsoft.Authorization/roleAssignments/13f2d62d-cc8b-4f0b-b204-d9e2120cb014",
              "Name": "13f2d62d-cc8b-4f0b-b204-d9e2120cb014",
              "properties": {
                "DisplayName": "AzOpsTF",
                "ObjectType": "ServicePrincipal",
                "PrincipalId": "4c4b17c2-26c9-49a0-a122-6c51177bede3",
                "RoleDefinitionId": "/providers/Microsoft.Authorization/RoleDefinitions/8e3af657-a8ff-443c-a75c-2fe8c4bcb635",
                "RoleDefinitionName": "Owner"
              },
              "ResourceType": "Microsoft.Authorization/roleAssignments"
            }
          ]
        }
      }
    }
  }
}
